parsomics_api_server/__init__.py
parsomics_api_server/api.py
parsomics_api_server/dependencies.py
parsomics_api_server/entities/_helpers.py
parsomics_api_server/entities/files/drep/_directory_router.py
parsomics_api_server/entities/files/drep/_entry_router.py
parsomics_api_server/entities/files/drep/router.py
parsomics_api_server/entities/files/fasta/_entry_router.py
parsomics_api_server/entities/files/fasta/_file_router.py
parsomics_api_server/entities/files/fasta/router.py
parsomics_api_server/entities/files/gene_annotation/_entry_router.py
parsomics_api_server/entities/files/gene_annotation/_file_router.py
parsomics_api_server/entities/files/gene_annotation/router.py
parsomics_api_server/entities/files/gff/_entry_router.py
parsomics_api_server/entities/files/gff/_file_router.py
parsomics_api_server/entities/files/gff/router.py
parsomics_api_server/entities/files/gtdbtk/_entry_router.py
parsomics_api_server/entities/files/gtdbtk/_file_router.py
parsomics_api_server/entities/files/gtdbtk/router.py
parsomics_api_server/entities/files/protein_annotation/_entry_router.py
parsomics_api_server/entities/files/protein_annotation/_file_router.py
parsomics_api_server/entities/files/protein_annotation/router.py
parsomics_api_server/entities/files/router.py
parsomics_api_server/entities/omics/contig/router.py
parsomics_api_server/entities/omics/fragment/router.py
parsomics_api_server/entities/omics/fragment_protein_link/router.py
parsomics_api_server/entities/omics/gene/router.py
parsomics_api_server/entities/omics/genome/router.py
parsomics_api_server/entities/omics/genome_cluster/router.py
parsomics_api_server/entities/omics/protein/router.py
parsomics_api_server/entities/omics/repeated_region/router.py
parsomics_api_server/entities/omics/router.py
parsomics_api_server/entities/omics/sample/router.py
parsomics_api_server/entities/router.py
parsomics_api_server/entities/workflow/assembly/router.py
parsomics_api_server/entities/workflow/metadata/router.py
parsomics_api_server-3.1.0.dist-info/METADATA
parsomics_api_server-3.1.0.dist-info/WHEEL
parsomics_api_server-3.1.0.dist-info/RECORD
