Metadata-Version: 2.3
Name: parsomics-api-server
Version: 3.1.0
Summary: A REST API server for parsomics
License: GPL-3.0
Author: Pedro Sader Azevedo
Author-email: pedro.saderazevedo@lnbr.cnpem.br
Requires-Python: >=3.12,<4.0
Classifier: License :: OSI Approved :: GNU General Public License v3 (GPLv3)
Classifier: Programming Language :: Python :: 3
Classifier: Programming Language :: Python :: 3.12
Classifier: Programming Language :: Python :: 3.13
Requires-Dist: fastapi[standard] (>=0.115.0,<0.116.0)
Requires-Dist: parsomics-core (>=4.1.0,<5.0.0)
Requires-Dist: sqlmodel (>=0.0.22,<0.0.23)
Requires-Dist: sqlmodel-query-builder (>=0.0.2,<0.0.3)
